video_music_remover/__init__.py
video_music_remover/cli.py
video_music_remover/common.py
video_music_remover/events.py
video_music_remover/ffmpeg.py
video_music_remover/main.py
video_music_remover/music_remover_models.py
video_music_remover/orms/__init__.py
video_music_remover/orms/demucs.py
video_music_remover/orms/ffmpeg.py
video_music_remover-1.1.3.dist-info/METADATA
video_music_remover-1.1.3.dist-info/WHEEL
video_music_remover-1.1.3.dist-info/entry_points.txt
video_music_remover-1.1.3.dist-info/licenses/LICENSE
video_music_remover-1.1.3.dist-info/RECORD
