Metadata-Version: 2.4
Name: video-music-remover
Version: 1.1.3
Summary: a cli tool to remove music from videos
Project-URL: Homepage, https://github.com/asaah18/video-music-remover
Project-URL: Repository, https://github.com/asaah18/video-music-remover.git
Project-URL: Issues, https://github.com/asaah18/video-music-remover/issues
Project-URL: changelog, https://github.com/asaah18/video-music-remover/blob/main/CHANGELOG.md
Author-email: ash <asaah18@gmail.com>
License-Expression: MIT
License-File: LICENSE
Keywords: music remover,no music,remove music from video,video music remover
Classifier: Development Status :: 5 - Production/Stable
Classifier: Intended Audience :: End Users/Desktop
Classifier: Operating System :: OS Independent
Classifier: Programming Language :: Python :: 3.10
Classifier: Programming Language :: Python :: 3.11
Classifier: Programming Language :: Python :: 3.12
Classifier: Programming Language :: Python :: 3.13
Requires-Python: >=3.10
Requires-Dist: demucs>=4.0.1
Requires-Dist: pydantic>=2.10.6
Requires-Dist: typer>=0.15.1
